fiftyone_devicedetection/__init__.py
fiftyone_devicedetection/devicedetection_pipelinebuilder.py
fiftyone_devicedetection-4.5.18.dist-info/METADATA
fiftyone_devicedetection-4.5.18.dist-info/WHEEL
fiftyone_devicedetection-4.5.18.dist-info/top_level.txt
fiftyone_devicedetection-4.5.18.dist-info/RECORD
